gbpautomation/__init__.py
gbpautomation/heat/__init__.py
gbpautomation/heat/db/__init__.py
gbpautomation/heat/db/sqlalchemy/__init__.py
gbpautomation/heat/db/sqlalchemy/migrate_repo/__init__.py
gbpautomation/heat/db/sqlalchemy/migrate_repo/versions/__init__.py
gbpautomation/heat/engine/__init__.py
gbpautomation/heat/engine/clients/__init__.py
gbpautomation/heat/engine/clients/os/__init__.py
gbpautomation/heat/engine/clients/os/grouppolicy.py
gbpautomation/heat/engine/resources/__init__.py
gbpautomation/heat/engine/resources/gbpresource.py
gbpautomation/heat/engine/resources/grouppolicy.py
gbpautomation/heat/engine/resources/servicechain.py
gbpautomation/heat/tests/__init__.py
gbpautomation/heat/tests/base.py
gbpautomation/heat/tests/test_gbpautomation.py
gbpautomation/heat/tests/test_grouppolicy.py
gbpautomation/heat/tests/test_servicechain.py
group_based_policy_automation-2015.2.2.dist-info/DESCRIPTION.rst
group_based_policy_automation-2015.2.2.dist-info/METADATA
group_based_policy_automation-2015.2.2.dist-info/RECORD
group_based_policy_automation-2015.2.2.dist-info/WHEEL
group_based_policy_automation-2015.2.2.dist-info/entry_points.txt
group_based_policy_automation-2015.2.2.dist-info/metadata.json
group_based_policy_automation-2015.2.2.dist-info/pbr.json
group_based_policy_automation-2015.2.2.dist-info/top_level.txt
